LICENSE
README.md
setup.py
carma.egg-info/PKG-INFO
carma.egg-info/SOURCES.txt
carma.egg-info/dependency_links.txt
carma.egg-info/requires.txt
carma.egg-info/top_level.txt
karma/UploadResult.py
karma/__init__.py
karma/__main__.py
karma/cloud_mail_api/__init__.py
karma/cloud_mail_api/errors.py
karma/cloud_mail_api/api/__init__.py
karma/cloud_mail_api/api/api_config.json
karma/cloud_mail_api/api/file.py
karma/cloud_mail_api/api/folder.py
karma/cloud_mail_api/api/generic.py
karma/cloud_mail_api/api/notify.py
karma/cloud_mail_api/api/single.py
karma/cloud_mail_api/api/tokens.py
karma/cloud_mail_api/api/trashbin.py