Metadata-Version: 2.1
Name: carma
Version: 0.0.3
Summary: Cli tool for managing cloud mail.ru storage
Home-page: https://github.com/zeionara/karma
Author: Zeio Nara
Author-email: zeionara@gmail.com
License: MIT
Project-URL: Documentation, https://github.com/zeionara/karma#readme
Project-URL: Bug Reports, https://github.com/zeionara/karma/issues
Project-URL: Source Code, https://github.com/zeionara/karma
Classifier: Intended Audience :: Developers
Classifier: License :: OSI Approved :: MIT License
Classifier: Programming Language :: Python :: 3.11
License-File: LICENSE
